LICENSE
README.rst
requirements.txt
setup.py
numphy/__init__.py
numphy/__init__.pyc
numphy.egg-info/PKG-INFO
numphy.egg-info/SOURCES.txt
numphy.egg-info/dependency_links.txt
numphy.egg-info/not-zip-safe
numphy.egg-info/top_level.txt