Metadata-Version: 1.1
Name: numphy
Version: 0.0.1
Summary: NumPy-backed physics objects.
Home-page: https://github.com/riga/numphy
Author: Marcel Rieger
Author-email: python-scinum@googlegroups.com
License: MIT
Keywords: numpy physics particle vector lorentz
Platform: UNKNOWN
Classifier: Programming Language :: Python
Classifier: Programming Language :: Python :: 2
Classifier: Programming Language :: Python :: 3
Classifier: Development Status :: 4 - Beta
Classifier: Operating System :: OS Independent
Classifier: License :: OSI Approved :: MIT License
Classifier: Intended Audience :: Developers
Classifier: Intended Audience :: Science/Research
Classifier: Intended Audience :: Information Technology
